tingg_checkout/__init__.py
tingg_checkout/checkout.py
tingg_checkout/constants.py
tingg_checkout/encryption.py
tingg_checkout/express.py
tingg_checkout/validation.py
checkout_python_sdk-0.2.0.dist-info/LICENSE
checkout_python_sdk-0.2.0.dist-info/METADATA
checkout_python_sdk-0.2.0.dist-info/WHEEL
checkout_python_sdk-0.2.0.dist-info/top_level.txt
checkout_python_sdk-0.2.0.dist-info/RECORD
